llama_index/_bundle/__init__.py
llama_index_test_starter-0.10.0.dist-info/LICENSE
llama_index_test_starter-0.10.0.dist-info/METADATA
llama_index_test_starter-0.10.0.dist-info/WHEEL
llama_index_test_starter-0.10.0.dist-info/entry_points.txt
llama_index_test_starter-0.10.0.dist-info/RECORD
